crmsh/__init__.py
crmsh/bootstrap.py
crmsh/cache.py
crmsh/cibconfig.py
crmsh/cibstatus.py
crmsh/cibverify.py
crmsh/clidisplay.py
crmsh/cliformat.py
crmsh/cmd_status.py
crmsh/command.py
crmsh/completers.py
crmsh/config.py
crmsh/constants.py
crmsh/corosync.py
crmsh/crm_gv.py
crmsh/crm_pssh.py
crmsh/handles.py
crmsh/help.py
crmsh/history.py
crmsh/idmgmt.py
crmsh/log_patterns.py
crmsh/logparser.py
crmsh/logtime.py
crmsh/main.py
crmsh/minieval.py
crmsh/msg.py
crmsh/options.py
crmsh/ordereddict.py
crmsh/orderedset.py
crmsh/pacemaker.py
crmsh/parse.py
crmsh/ra.py
crmsh/rsctest.py
crmsh/schema.py
crmsh/scripts.py
crmsh/template.py
crmsh/term.py
crmsh/tmpfiles.py
crmsh/ui_assist.py
crmsh/ui_cib.py
crmsh/ui_cibstatus.py
crmsh/ui_cluster.py
crmsh/ui_configure.py
crmsh/ui_context.py
crmsh/ui_corosync.py
crmsh/ui_history.py
crmsh/ui_maintenance.py
crmsh/ui_node.py
crmsh/ui_options.py
crmsh/ui_ra.py
crmsh/ui_report.py
crmsh/ui_resource.py
crmsh/ui_root.py
crmsh/ui_script.py
crmsh/ui_site.py
crmsh/ui_template.py
crmsh/ui_utils.py
crmsh/userdir.py
crmsh/utils.py
crmsh/xmlutil.py
crmsh_boot-0.1.data/scripts/crm
crmsh_boot-0.1.dist-info/METADATA
crmsh_boot-0.1.dist-info/RECORD
crmsh_boot-0.1.dist-info/WHEEL
crmsh_boot-0.1.dist-info/top_level.txt
usr/share/crmsh/crm.8.adoc
