Metadata-Version: 2.1
Name: crmsh-boot
Version: 0.1
Summary: Command-line interface to bootstrap cluster
Home-page: http://crmsh.github.io/
Author: Kristoffer Gronlund; Xin Liang
Author-email: XLiang@suse.com
License: UNKNOWN
Platform: UNKNOWN
